miner2/__init__.py
miner2/coexpression.py
miner2/mechanistic_inference.py
miner2/miner.py
miner2/preprocess.py
miner2/data/identifier_mappings.txt
miner2/data/tfbsdb_tf_to_genes.pkl
miner2-0.0.9.data/scripts/miner-bcmembers
miner2-0.0.9.data/scripts/miner-causalinf-post
miner2-0.0.9.data/scripts/miner-causalinf-pre
miner2-0.0.9.data/scripts/miner-coexpr
miner2-0.0.9.data/scripts/miner-mechinf
miner2-0.0.9.data/scripts/miner-neo
miner2-0.0.9.data/scripts/miner-subtypes
miner2-0.0.9.data/scripts/miner-survival
miner2-0.0.9.dist-info/LICENSE
miner2-0.0.9.dist-info/METADATA
miner2-0.0.9.dist-info/WHEEL
miner2-0.0.9.dist-info/top_level.txt
miner2-0.0.9.dist-info/RECORD
